eric-verysimplemodule/__init__.py
eric-verysimplemodule/add.py
eric-verysimplemodule/subtract.py
eric-verysimplemodule/extras/__init__.py
eric-verysimplemodule/extras/divide.py
eric-verysimplemodule/extras/multiply.py
verysimplemodule/__init__.py
verysimplemodule/add.py
verysimplemodule/subtract.py
verysimplemodule/extras/__init__.py
verysimplemodule/extras/divide.py
verysimplemodule/extras/multiply.py
eric_verysimplemodule-0.0.1.dist-info/METADATA
eric_verysimplemodule-0.0.1.dist-info/WHEEL
eric_verysimplemodule-0.0.1.dist-info/top_level.txt
eric_verysimplemodule-0.0.1.dist-info/RECORD
